fireredasr/__init__.py
fireredasr/data/__init__.py
fireredasr/data/asr_feat.py
fireredasr/data/token_dict.py
fireredasr/models/__init__.py
fireredasr/models/fireredasr.py
fireredasr/models/fireredasr_aed.py
fireredasr/models/fireredasr_llm.py
fireredasr/models/module/__init__.py
fireredasr/models/module/adapter.py
fireredasr/models/module/conformer_encoder.py
fireredasr/models/module/transformer_decoder.py
fireredasr/tokenizer/__init__.py
fireredasr/tokenizer/aed_tokenizer.py
fireredasr/tokenizer/llm_tokenizer.py
fireredasr/utils/__init__.py
fireredasr/utils/param.py
fireredasr/utils/wer.py
fireredasr-0.0.2.dist-info/LICENSE
fireredasr-0.0.2.dist-info/METADATA
fireredasr-0.0.2.dist-info/WHEEL
fireredasr-0.0.2.dist-info/top_level.txt
fireredasr-0.0.2.dist-info/RECORD
